pygleif/VERSION
pygleif/__init__.py
pygleif/base.py
pygleif/error.py
pygleif/gleif.py
pygleif/py.typed
pygleif/search.py
pygleif/api/__init__.py
pygleif/api/data.py
pygleif/api/meta.py
pygleif/api/shared.py
pygleif-2025.7.1.dist-info/licenses/LICENSE
script/__init__.py
script/example_lookup.py
pygleif-2025.7.1.dist-info/METADATA
pygleif-2025.7.1.dist-info/WHEEL
pygleif-2025.7.1.dist-info/top_level.txt
pygleif-2025.7.1.dist-info/RECORD
