Metadata-Version: 2.4
Name: pygleif
Version: 2025.7.1
Summary: Query the GLEIF API using Python
Author-email: ggravlingen <no@email.com>
License: MIT
Project-URL: Source Code, https://github.com/ggravlingen/pygleif
Keywords: lei-code,lei,api,gleif,leicode
Platform: any
Classifier: Development Status :: 5 - Production/Stable
Classifier: Natural Language :: English
Classifier: Programming Language :: Python :: 3
Classifier: Programming Language :: Python :: 3.11
Classifier: Programming Language :: Python :: 3.12
Classifier: Intended Audience :: Financial and Insurance Industry
Requires-Python: >=3.11
License-File: LICENSE
Requires-Dist: pydantic<3,>2
Provides-Extra: test
Requires-Dist: coverage==7.9.1; extra == "test"
Requires-Dist: mypy==1.16.1; extra == "test"
Requires-Dist: pre-commit==4.2.0; extra == "test"
Requires-Dist: ruff==0.12.1; extra == "test"
Requires-Dist: pytest==8.4.1; extra == "test"
Requires-Dist: pytest-cov==6.2.1; extra == "test"
Dynamic: license-file
